cog_reloader/__init__.py
cog_reloader/cog.py
cog_reloader-0.0.2.dist-info/LICENSE
cog_reloader-0.0.2.dist-info/METADATA
cog_reloader-0.0.2.dist-info/WHEEL
cog_reloader-0.0.2.dist-info/top_level.txt
cog_reloader-0.0.2.dist-info/RECORD
