Metadata-Version: 2.1
Name: cog-reloader
Version: 0.0.2
Summary: Make reloading cogs easy while editing. Compitable with `nextcord` and `discord.py`
Home-page: https://github.com/shahriyardx/cog-relaoder/
Author: Md Shahriyar Alam
Author-email: mdshahriyaralam552@gmail.com
License: MIT
Keywords: discord discord.py nextcord.py nextcord
Platform: UNKNOWN
Classifier: Development Status :: 5 - Production/Stable
Classifier: Operating System :: POSIX :: Linux
Classifier: Operating System :: Microsoft :: Windows
Classifier: Operating System :: MacOS
Classifier: License :: OSI Approved :: MIT License
Classifier: Programming Language :: Python :: 3
Requires-Python: >=3.8.0
